{"GlobalPropertiesHash":"MnE51l4hE+h0HATfsCxdpGlkkohcwNC/HchNT3+z7hQ=","FingerprintPatternsHash":"gq3WsqcKBUGTSNle7RKKyXRIwh7M8ccEqOqYvIzoM04=","PropertyOverridesHash":"8ZRc1sGeVrPBx4lD717BgRaQekyh78QKV9SKsdt638U=","InputHashes":["fQTWuecNKX3DNtQYKpK/u3ugikZfeWhnSLYm94J1tP4=","b4KpLWQeoXRjHCr4A9zm0SLt+w6g5gdftf2iVspkayE=","LhKW1PUVIMSD3qBMS/jApvnGPBmsq8P6HrxwRKNlUyI=","gkoU++yNVmlc5AQq38ePsQUH3TIobFH4HgGtCCCCCI0=","/XegLktKg6bvJvbIhjP545enmSiA2d6Hhcs39gX754E=","+FZ0Wzdnj/mQxvVfKWGSa/nmkTFo55famcz3uuyXPPM="],"CachedAssets":{"fQTWuecNKX3DNtQYKpK/u3ugikZfeWhnSLYm94J1tP4=":{"Identity":"E:\\Source\\MauiBlazor\\DailyPoetryHybrid.Library\\wwwroot\\background.png","SourceId":"DailyPoetryHybrid.Library","SourceType":"Discovered","ContentRoot":"E:\\Source\\MauiBlazor\\DailyPoetryHybrid.Library\\wwwroot\\","BasePath":"_content/DailyPoetryHybrid.Library","RelativePath":"background#[.{fingerprint}]?.png","AssetKind":"All","AssetMode":"All","AssetRole":"Primary","AssetMergeBehavior":null,"AssetMergeSource":"","RelatedAsset":null,"AssetTraitName":null,"AssetTraitValue":null,"Fingerprint":"x2rx4ajns0","Integrity":"WeOKCkI7IdJHs2kCqsKgLfiWX4/sNPbaRUspOLefkCY=","CopyToOutputDirectory":"Never","CopyToPublishDirectory":"PreserveNewest","OriginalItemSpec":"wwwroot\\background.png","FileLength":378,"LastWriteTime":"2026-02-28T09:07:38+00:00"},"b4KpLWQeoXRjHCr4A9zm0SLt+w6g5gdftf2iVspkayE=":{"Identity":"E:\\Source\\MauiBlazor\\DailyPoetryHybrid.Library\\wwwroot\\exampleJsInterop.js","SourceId":"DailyPoetryHybrid.Library","SourceType":"Discovered","ContentRoot":"E:\\Source\\MauiBlazor\\DailyPoetryHybrid.Library\\wwwroot\\","BasePath":"_content/DailyPoetryHybrid.Library","RelativePath":"exampleJsInterop#[.{fingerprint}]?.js","AssetKind":"All","AssetMode":"All","AssetRole":"Primary","AssetMergeBehavior":null,"AssetMergeSource":"","RelatedAsset":null,"AssetTraitName":null,"AssetTraitValue":null,"Fingerprint":"6pqz8bsss0","Integrity":"FrrTtczTUEHjkhc/zWRPC7CmxeXI0JCZGc1+76qQ8B4=","CopyToOutputDirectory":"Never","CopyToPublishDirectory":"PreserveNewest","OriginalItemSpec":"wwwroot\\exampleJsInterop.js","FileLength":247,"LastWriteTime":"2026-02-28T09:07:38+00:00"}},"CachedCopyCandidates":{}}